{
	"ImportPath": "github.com/swipely/iam-docker",
	"GoVersion": "go1.4",
	"Packages": [
		"./..."
	],
	"Deps": [
		{
			"ImportPath": "github.com/cihub/seelog",
			"Comment": "go1.1-57-g0fa7e41",
			"Rev": "0fa7e41d2b9600ca6b7e1592478124e4f800f724"
		},
		{
			"ImportPath": "github.com/fsouza/go-dockerclient",
			"Rev": "134c9ac46b51ace9135c81efe9aa9895d346c1cf"
		},
		{
			"ImportPath": "github.com/onsi/ginkgo",
			"Comment": "v1.2.0-11-gd94e2f4",
			"Rev": "d94e2f4000332f62b356ecb2840c98f4218f5358"
		},
		{
			"ImportPath": "github.com/onsi/gomega",
			"Comment": "v1.0-52-ga2ab864",
			"Rev": "a2ab8644e0b6a33df2cbe44673bd0f6ebba9abc3"
		}
	]
}
